[
    {
        "id": "ip",
        "type": "text",
        "label": { 
            "en": "IP address",
            "de": "IP-Adresse"
        },
        "value": ""
    },
    {
        "id": "port",
        "type": "number",
        "label": { 
            "en": "Port",
            "de": "Port"
        },
        "value": 502
    },
    {
        "id": "id",
        "type": "number",
        "label": { 
            "en": "ID",
            "de": "ID"
        },
        "value": 1
    },
    {
        "id": "connection",
        "type": "dropdown",
        "label": { 
            "en": "Connection type",
            "de": "Verbindunsgtyp"
        },
        "value": "keep",
        "values":[
            {
                "id": "keep",
                "label":{ 
                    "en": "Keep connection",
                    "de": "Verbindung aufrecht erhalten"
                }
            },
            {
                "id": "single",
                "label":{ 
                    "en": "Single connect",
                    "de": "Einzelverbindung"
                }
            },
            {
                "id": "manually",
                "label":{ 
                    "en": "Manually",
                    "de": "Manuell"
                }
            }
        ]
    }
]